COPYING
COPYING.LESSER
MANIFEST.in
README.rst
package.py
requirements.txt
setup.cfg
setup.py
version
QuickBean.egg-info/PKG-INFO
QuickBean.egg-info/SOURCES.txt
QuickBean.egg-info/dependency_links.txt
QuickBean.egg-info/requires.txt
QuickBean.egg-info/top_level.txt
quickbean/__init__.py