Metadata-Version: 1.0
Name: QuickBean
Version: 1.7.1
Summary: A library that reduces the boilerplate code required to define beans.
Home-page: https://bitbucket.org/okozak/quickbean
Author: Olivier Kozak
Author-email: olivier.kozak@gmail.com
License: GNU LGPL v3
Platform: UNKNOWN
